smdv.py
smdv-0.1.1.dist-info/METADATA
smdv-0.1.1.dist-info/WHEEL
smdv-0.1.1.dist-info/entry_points.txt
smdv-0.1.1.dist-info/top_level.txt
smdv-0.1.1.dist-info/RECORD
