Metadata-Version: 2.1
Name: smdv
Version: 0.1.1
Summary: smdv: a simple markdown viewer 
Home-page: https://github.com/flaport/smdv
Author: Floris Laporte
Author-email: floris.laporte@gmail.com
License: UNKNOWN
Platform: UNKNOWN
Classifier: Topic :: Utilities
Classifier: Intended Audience :: End Users/Desktop
Classifier: Intended Audience :: Developers
Classifier: Programming Language :: Python :: 3
Classifier: Operating System :: POSIX :: Linux
Classifier: License :: OSI Approved :: GNU General Public License v3 (GPLv3)
Requires-Python: >=3.6
Requires-Dist: flask
Requires-Dist: websockets
